exoscraper/__init__.py
exoscraper/distribution.py
exoscraper/planet.py
exoscraper/population.py
exoscraper/query.py
exoscraper/star.py
exoscraper/system.py
exoscraper/utils.py
exoscraper-0.2.1.dist-info/METADATA
exoscraper-0.2.1.dist-info/WHEEL
exoscraper-0.2.1.dist-info/licenses/LICENSE
exoscraper-0.2.1.dist-info/RECORD
