Metadata-Version: 2.4
Name: exoscraper
Version: 0.2.1
Summary: Package to scrape data on exoplanet targets to help you build your mission.
License: MIT
License-File: LICENSE
Author: Your Name
Author-email: you@example.com
Requires-Python: >=3.9,<4.0
Classifier: License :: OSI Approved :: MIT License
Classifier: Programming Language :: Python :: 3
Classifier: Programming Language :: Python :: 3.9
Classifier: Programming Language :: Python :: 3.10
Classifier: Programming Language :: Python :: 3.11
Classifier: Programming Language :: Python :: 3.12
Classifier: Programming Language :: Python :: 3.13
Classifier: Programming Language :: Python :: 3.14
Requires-Dist: astropy (>=5.3.3,<7.0)
Requires-Dist: astroquery (>=0.4.6,<0.5.0)
Requires-Dist: batman-package (>=2.4.9,<3.0.0)
Requires-Dist: beautifulsoup4 (>=4.12.2,<5.0.0)
Requires-Dist: gaiaoffline (>=1.0.3)
Requires-Dist: pandas (>=2.1.3,<3.0.0)
Requires-Dist: requests (>=2.32.3,<3.0.0)
Requires-Dist: rich (>=13.4.2,<14.0.0)
